rna_count_salmon-1.9.data/scripts/rna-count-salmon.py
scripts/__init__.py
scripts/common_script_rna_count_salmon.py
scripts/prepare_config.py
scripts/prepare_design.py
rna_count_salmon-1.9.dist-info/LICENSE
rna_count_salmon-1.9.dist-info/METADATA
rna_count_salmon-1.9.dist-info/WHEEL
rna_count_salmon-1.9.dist-info/top_level.txt
rna_count_salmon-1.9.dist-info/RECORD
