Metadata-Version: 2.1
Name: rna-count-salmon
Version: 1.9
Summary: rna-count-salmon is a pipeline written with  Snakemake that quantifies your RNA-Seq reads with Salmon, controls input quality with FastQC, and gathers qualities with MultiQC.
Home-page: https://github.com/tdayris-perso/rna-count-salmon/wiki
Author: Thibault Dayris
Author-email: thibault.dayris@gustaveroussy.fr
License: GPLv3
Platform: UNKNOWN
Classifier: Environment :: Console
Classifier: Natural Language :: English
Classifier: Programming Language :: Python :: 3.7
Classifier: Topic :: Scientific/Engineering :: Bio-Informatics
Classifier: Development Status :: 5 - Production/Stable
Requires-Python: >=3.7
Requires-Dist: conda
Requires-Dist: datrie (==0.8.2)
Requires-Dist: jinja2 (==2.11.2)
Requires-Dist: flask (==1.1.2)
Requires-Dist: pandas (==1.0.3)
Requires-Dist: snakemake (==5.19.3)
Requires-Dist: pytest (==5.4.2)
